Workbook

Sheet Budget Summary
A1: Experimental Budget: Token & Cost Estimation
A4: Role assignment
A5: GENERATOR ROLES - all 3 models independently run the FULL task list (SS4). The token pool below (Generation Tokens sheet) represents ONE model's complete workload; each generator row takes 100% of it, and the 3 rows sum to the true 3-model total. Do not set these below 100% unless a model is only doing a partial run.
A7: Role | B7: Model (dropdown) | C7: Generators: | D7: Input tokens (allocated) | E7: Output tokens (allocated) | F7: Input €/MTok | G7: Output €/MTok | H7: Cost (€)
A8: Frontier generator | B8: GPT-5.6 Sol | C8: 1
A9: EU open-weight generator #1 | B9: Mistral Medium 3.5 | C9: 1
A10: EU open-weight generator #2 (optional — set share to 0 if not used) | B10: Gemini 3.8 Flash | C10: 1
A14: Role | B14: Model (dropdown) | C14: Judges: | D14: Input tokens (allocated) | E14: Output tokens (allocated) | F14: Input €/MTok | G14: Output €/MTok | H14: Cost (€)
A15: Judge family 1 | B15: Claude Opus 5 | C15: 0.34
A16: Judge family 2 | B16: Qwen3.8 Max (0902) | C16: 0.33
A17: Judge family 3 | B17: Kimi K3 | C17: 0.33
A18: Judge shares sum check: | B18: =IF(ROUND(C15+C16+C17,4)<>1,"WARNING: judge shares sum to "&TEXT(C15+C16+C17,"0%")&", not 100% of the combined pool -- since the pool is already 3-judges-worth, shares must sum to 100% (not each be 100%) or tokens will be mis-counted","OK: judge shares sum to 100% of the combined 3-judge pool (each judge's own full pass)") -> OK: judge shares sum to 100% of the combined 3-judge pool (each judge's own full pass)
A19: Generator/judge overlap check: | B19: =IF(OR(($B$8=$B$15),($B$8=$B$16),($B$8=$B$17),($B$9=$B$15),($B$9=$B$16),($B$9=$B$17),($B$10=$B$15),($B$10=$B$16),($B$10=$B$17)),"WARNING: a judge model matches a generator model","OK: judge pool disjoint from generator pool") -> OK: judge pool disjoint from generator pool
A20: Generator full-replication check: | B20: =IF(OR(AND(B8<>"",C8<>1),AND(B9<>"",C9<>1),AND(B10<>"",C10<>1)),"WARNING: a generator role is not at 100% -- the pool represents ONE model's workload, so each assigned generator should be 100% (3 rows correctly sum to 300% = 3x total, since 3 full independent models run)","OK: all assigned generators at 100% (pool=1 model's workload, 3 rows replicate to true 3-model total)") -> OK: all assigned generators at 100% (pool=1 model's workload, 3 rows replicate to true 3-model total)
A21: Cost by assigned model (standard / non-batch pricing)
A23: Model (from role rows above) | B23: Role | C23: Runs full workload | D23: Input Tokens | E23: Output Tokens | F23: Input €/MTok | G23: Output €/MTok | H23: Cost (€, standard)
A24: =B8 -> GPT-5.6 Sol | B24: =A8 -> Frontier generator | C24: =C8 -> 1 | D24: ='Generation Tokens'!H$17*C8 -> 3669900 | E24: ='Generation Tokens'!I$17*C8 -> 5156250 | F24: =IFERROR(INDEX('Model Registry'!$F$7:$F$23,MATCH($B$8,'Model Registry'!$A$7:$A$23,0)),0) -> 3.68 | G24: =IFERROR(INDEX('Model Registry'!$G$7:$G$23,MATCH($B$8,'Model Registry'!$A$7:$A$23,0)),0) -> 18.4 | H24: =(D24/1000000*F24)+(E24/1000000*G24) -> 108.38023
A25: =B9 -> Mistral Medium 3.5 | B25: =A9 -> EU open-weight generator #1 | C25: =C9 -> 1 | D25: ='Generation Tokens'!H$17*C9 -> 3669900 | E25: ='Generation Tokens'!I$17*C9 -> 5156250 | F25: =IFERROR(INDEX('Model Registry'!$F$7:$F$23,MATCH($B$9,'Model Registry'!$A$7:$A$23,0)),0) -> 1.38 | G25: =IFERROR(INDEX('Model Registry'!$G$7:$G$23,MATCH($B$9,'Model Registry'!$A$7:$A$23,0)),0) -> 6.9 | H25: =(D25/1000000*F25)+(E25/1000000*G25) -> 40.642587
A26: =B10 -> Gemini 3.8 Flash | B26: =A10 -> EU open-weight generator #2 (optional — set share to 0 if not used) | C26: =C10 -> 1 | D26: ='Generation Tokens'!H$17*C10 -> 3669900 | E26: ='Generation Tokens'!I$17*C10 -> 5156250 | F26: =IFERROR(INDEX('Model Registry'!$F$7:$F$23,MATCH($B$10,'Model Registry'!$A$7:$A$23,0)),0) -> 0.69 | G26: =IFERROR(INDEX('Model Registry'!$G$7:$G$23,MATCH($B$10,'Model Registry'!$A$7:$A$23,0)),0) -> 3.45 | H26: =(D26/1000000*F26)+(E26/1000000*G26) -> 20.321293
A27: =B15 -> Claude Opus 5 | B27: =A15 -> Judge family 1 | C27: =C15 -> 0.34 | D27: ='Judging Tokens'!E$12*C15 -> 9412560 | E27: ='Judging Tokens'!F$12*C15 -> 203796 | F27: =IFERROR(INDEX('Model Registry'!$F$7:$F$23,MATCH($B$15,'Model Registry'!$A$7:$A$23,0)),0) -> 4.6 | G27: =IFERROR(INDEX('Model Registry'!$G$7:$G$23,MATCH($B$15,'Model Registry'!$A$7:$A$23,0)),0) -> 23 | H27: =(D27/1000000*F27)+(E27/1000000*G27) -> 47.985084
A28: =B16 -> Qwen3.8 Max (0902) | B28: =A16 -> Judge family 2 | C28: =C16 -> 0.33 | D28: ='Judging Tokens'!E$12*C16 -> 9135720 | E28: ='Judging Tokens'!F$12*C16 -> 197802 | F28: =IFERROR(INDEX('Model Registry'!$F$7:$F$23,MATCH($B$16,'Model Registry'!$A$7:$A$23,0)),0) -> 1.84 | G28: =IFERROR(INDEX('Model Registry'!$G$7:$G$23,MATCH($B$16,'Model Registry'!$A$7:$A$23,0)),0) -> 5.52 | H28: =(D28/1000000*F28)+(E28/1000000*G28) -> 17.901592
A29: =B17 -> Kimi K3 | B29: =A17 -> Judge family 3 | C29: =C17 -> 0.33 | D29: ='Judging Tokens'!E$12*C17 -> 9135720 | E29: ='Judging Tokens'!F$12*C17 -> 197802 | F29: =IFERROR(INDEX('Model Registry'!$F$7:$F$23,MATCH($B$17,'Model Registry'!$A$7:$A$23,0)),0) -> 0.552 | G29: =IFERROR(INDEX('Model Registry'!$G$7:$G$23,MATCH($B$17,'Model Registry'!$A$7:$A$23,0)),0) -> 2.3 | H29: =(D29/1000000*F29)+(E29/1000000*G29) -> 5.497862
A30: TOTAL (standard pricing, no batch discount) | D30: =SUM(D24:D29) -> 38693700 | E30: =SUM(E24:E29) -> 16068150 | H30: =SUM(H24:H29) -> 240.72865
A32: Zero-priced-model check: | B32: =IF(OR(AND(C24>0,F24=0,G24=0),AND(C25>0,F25=0,G25=0),AND(C26>0,F26=0,G26=0),AND(C27>0,F27=0,G27=0),AND(C28>0,F28=0,G28=0),AND(C29>0,F29=0,G29=0)),"NOTE: one or more assigned models show €0/€0 — likely a self-host-only EU model (TildeOpen/EuroLLM). Fill in HPC marginal cost below, or a confirmed inference-provider rate on Model Registry, before treating totals as complete.","OK: all assigned models with nonzero share have a nonzero rate (hosted or filled-in)") -> OK: all assigned models with nonzero share have a nonzero rate (hosted or filled-in)
A34: HPC self-host override (use if a generator role is assigned an EU model with no hosted rate)
A35: If TildeOpen 30B or EuroLLM is assigned to a generator role above, its per-MTok cost resolves to €0 from the registry. Toggle below to instead charge that share's tokens at the HPC marginal-cost rate you set on Model Registry (row 29). This does NOT change the cost table above automatically (to keep that table a clean per-model audit trail) — it's a separate, explicit add-on line, so you can see both numbers.
A37: Apply HPC marginal cost to zero-priced generator shares? (1=yes, 0=no) | B37: 1
A38: HPC add-on cost (applies HPC €/GPU-hour-derived rate to any generator row priced €0/€0 above) | D38: =SUMPRODUCT((F24:F26=0)*(G24:G26=0)*(D24:D26+E24:E26)) -> 0 | H38: =B37*(D38/1000000)*'Model Registry'!$B$35 -> 0
A40: TOTAL incl. HPC add-on for self-hosted EU models | H40: =H30+H38 -> 240.72865
A42: With Batch API discount applied to judging calls (async-eligible; 50% typical)
A43: Judging is inherently offline/async — a strong Batch API candidate. Generation stages are often run interactively during development, so shown unchanged here as the conservative case.
A44: Judging cost at 50% (Batch API) | H44: =SUM(H27:H29)*0.5 -> 35.692269
A45: Generation cost (unchanged, standard pricing) | H45: =SUM(H24:H26) -> 169.34411
A46: TOTAL (judging batched, generation standard) | H46: =H44+H45 -> 205.03638
A48: Pilot run cost (SS7: 3 items/language, all tasks/conditions)
A49: Pilot is 6/30 source items = 20% of the main corpus by item count. Conservative upper-bound (pilot judging volume is typically smaller in practice).
A50: Estimated pilot cost (~20% of main-corpus item count, standard pricing) | H50: =H30*0.2 -> 48.14573

Sheet Model Registry
A1: Model Registry — the ONLY place model names/prices/roles are typed
A2: Every other sheet looks up rows from here by name (INDEX/MATCH). To rename, reprice, or swap a model: edit ONE row here. To add a model, add a row and extend the dropdown range on Budget Summary.
A4: USD -> EUR rate | B4: 0.92 | C4: update to current rate before finalizing
A6: Model name (edit here to rename) | B6: Category | C6: Input $/MTok | D6: Output $/MTok | E6: Batch discount | F6: Input €/MTok (auto) | G6: Output €/MTok (auto) | H6: Provider / hosting note
A7: GPT-5.6 Sol | B7: Frontier | C7: 4 | D7: 20 | E7: 0.5 | F7: =C7*$B$4 -> 3.68 | G7: =D7*$B$4 -> 18.4
A8: GPT-5.6 Terra | B8: Frontier | C8: 2 | D8: 12 | E8: 0.5 | F8: =C8*$B$4 -> 1.84 | G8: =D8*$B$4 -> 11.04
A9: GPT-5.6 Luna | B9: Frontier | C9: 0.2 | D9: 1.2 | E9: 0.5 | F9: =C9*$B$4 -> 0.184 | G9: =D9*$B$4 -> 1.104
A10: GPT-6 Astra | B10: Frontier | C10: 10 | D10: 50 | E10: 0.5 | F10: =C10*$B$4 -> 9.2 | G10: =D10*$B$4 -> 46
A11: Claude Sonnet 5 | B11: Frontier | C11: 2 | D11: 10 | E11: 0.5 | F11: =C11*$B$4 -> 1.84 | G11: =D11*$B$4 -> 9.2
A12: Claude Opus 5 | B12: Frontier | C12: 5 | D12: 25 | E12: 0.5 | F12: =C12*$B$4 -> 4.6 | G12: =D12*$B$4 -> 23
A13: Claude Haiku 4.5 | B13: Frontier | C13: 1 | D13: 5 | E13: 0.5 | F13: =C13*$B$4 -> 0.92 | G13: =D13*$B$4 -> 4.6
A14: Gemini 3.8 Flash | B14: Frontier | C14: 0.75 | D14: 3.75 | E14: n/a listed | F14: =C14*$B$4 -> 0.69 | G14: =D14*$B$4 -> 3.45
A15: Mistral Large 3 | B15: EU open-weight | C15: 0.5 | D15: 1.5 | E15: n/a listed | F15: =C15*$B$4 -> 0.46 | G15: =D15*$B$4 -> 1.38
A16: Mistral Medium 3.5 | B16: EU open-weight | C16: 1.5 | D16: 7.5 | E16: n/a listed | F16: =C16*$B$4 -> 1.38 | G16: =D16*$B$4 -> 6.9
A17: TildeOpen 30B | B17: EU open-weight | C17: 0 | D17: 0 | E17: n/a | F17: =C17*$B$4 -> 0 | G17: =D17*$B$4 -> 0
A18: EuroLLM (22B-class) | B18: EU open-weight | C18: 0 | D18: 0 | E18: n/a | F18: =C18*$B$4 -> 0 | G18: =D18*$B$4 -> 0
A19: Qwen3.8 Max (0902) | B19: Non-EU open-weight | C19: 2 | D19: 6 | E19: n/a listed | F19: =C19*$B$4 -> 1.84 | G19: =D19*$B$4 -> 5.52
A20: Kimi K3 | B20: Non-EU open-weight | C20: 0.6 | D20: 2.5 | E20: n/a listed | F20: =C20*$B$4 -> 0.552 | G20: =D20*$B$4 -> 2.3
A21: MiniMax M3 | B21: Non-EU open-weight | C21: 0.3 | D21: 1 | E21: n/a listed | F21: =C21*$B$4 -> 0.276 | G21: =D21*$B$4 -> 0.92
A22: GLM 5.2 | B22: Non-EU open-weight | C22: 0.5 | D22: 2 | E22: n/a listed | F22: =C22*$B$4 -> 0.46 | G22: =D22*$B$4 -> 1.84
A23: Llama 3.3 70B Instruct | B23: Non-EU open-weight | C23: 0.1 | D23: 0.4 | E23: n/a listed | F23: =C23*$B$4 -> 0.092 | G23: =D23*$B$4 -> 0.368
A25: (add new models below this line if needed; extend named range Model_Names and dropdown source accordingly)
A27: HPC self-hosting block — for EU open-weight models with no confirmed hosted API
A28: Applies to any model that we can and want to self-host for the experiments.
A31: Parameter | B31: Value | C31: Note
A32: GPU type assumed | B32: 1x A100 80GB or equiv. | C32: Set to your cluster's actual allocation unit
A33: Throughput (tok/s, batched, 30B-class EU model) | B33: 1800 | C33: Rough batched-serving estimate for a ~22-30B model on one A100; verify against your own vLLM/TGI stack once deployed
A34: External cloud-equivalent rate (EUR/GPU-hour) | B34: 2.2 | C34: e.g. an on-demand A100 rate, for opportunity-cost comparison only — your HPC allocation itself may be a sunk/grant-funded cost with €0 marginal price to the project
A35: Treat HPC marginal cost as (EUR) | B35: 0 | C35: Set to 0 if your HPC allocation is pre-paid/granted and has no per-use billback to this project; set to the external-rate-derived figure if you must account for opportunity cost or shared-cluster chargeback

Sheet Assumptions
A1: Token & Structural Assumptions
A3: Parameter | B3: Value | C3: Note
A4: tok_per_word | B4: 1.35 | C4: Average tokens/word across EN+NL, generous rounding
A5: story_tokens | B5: 2200 | C5: Representative story length (1200-2000 words -> ~1600-2700 tok; use mid-high)
A6: spec_tokens | B6: 2000 | C6: Full 36-sub-dim specification, in or out
A7: premise_tokens | B7: 130 | C7: Short premise paragraph
A8: plan_tokens | B8: 1000 | C8: Story outline/beat sheet output
A9: review_output_tokens | B9: 450 | C9: Structured critique output (review stage)
A10: repair_output_tokens | B10: 1800 | C10: Output tokens per repair pass (conservative: near-full redraft)
A11: avg_repair_passes | B11: 1.5 | C11: Average repair iterations per item, bounded by k_max (not all items hit max)
A12: dimension_list_tokens | B12: 150 | C12: Six dimension names + one-line definitions, used in A1 prompt
A13: prompt_overhead_tokens | B13: 250 | C13: System/instruction overhead added to every call, input side
A15: Structural counts (from design doc)
A16: n_source_items | B16: 30 | C16: SS2.1
A17: n_scratch_items | B17: 10 | C17: SS2.3
A18: n_genfamilies | B18: 3 | C18: Set to 1: full replication across models is now handled on Budget Summary (each generator role runs 100% of this ONE-model pool, and 3 role-rows sum together).
A19: n_judge_families | B19: 3 | C19: SS6 — none from the generator family set
A20: taskA_generated_conditions | B20: 5 | C20: C1,C2,C4,C5,C6 — C7 is the human item, not generated (correction to doc's literal '6')
A21: taskD_outputs_per_item | B21: 7 | C21: 1 scratch story + 6 variants, per doc SS4 (10x7x2=140)

Sheet Generation Tokens
A1: Generation-Side Token Estimate (per SS4 story counts)
A2: n_genfamilies now = 3 (frontier + up to 2 EU open-weight). Totals below are PER-GENERATOR-FAMILY-SUMMED; Budget Summary splits this pool across whichever specific models you assign to generator roles.
A4: Task / Condition | B4: # Items | C4: Multiplier | D4: # Generators | E4: Total Gen Events | F4: Input tok /event | G4: Output tok /event | H4: Total Input Tokens | I4: Total Output Tokens | J4: Note
A5: Task A: Story draft (5 generated conditions) | B5: =Assumptions!B16 -> 30 | C5: =Assumptions!B20 -> 5 | D5: =Assumptions!B18 -> 3 | E5: =B5*C5*D5 -> 450 | F5: =Assumptions!B13+Assumptions!B7 -> 380 | G5: =Assumptions!B5 -> 2200 | H5: =E5*F5 -> 171000 | I5: =E5*G5 -> 990000 | J5: Covers flat-call floor; C1/C2/C4 extra stages costed below
A6: Task A: C1/C2 spec-writing | B6: =Assumptions!B16 -> 30 | C6: 2 | D6: =Assumptions!B18 -> 3 | E6: =B6*C6*D6 -> 180 | F6: =Assumptions!B13+Assumptions!B7 -> 380 | G6: =Assumptions!B6 -> 2000 | H6: =E6*F6 -> 68400 | I6: =E6*G6 -> 360000 | J6: Mult=2 (C1,C2 only)
A7: Task A: Plan stage (C1,C2,C4) | B7: =Assumptions!B16 -> 30 | C7: 3 | D7: =Assumptions!B18 -> 3 | E7: =B7*C7*D7 -> 270 | F7: =Assumptions!B13+Assumptions!B6 -> 2250 | G7: =Assumptions!B8 -> 1000 | H7: =E7*F7 -> 607500 | I7: =E7*G7 -> 270000 | J7: Mult=3; C3/C5 skip plan, C6 unknown/excluded pending pilot
A8: Task A: Review stage (C1,C4) | B8: =Assumptions!B16 -> 30 | C8: 2 | D8: =Assumptions!B18 -> 3 | E8: =B8*C8*D8 -> 180 | F8: =Assumptions!B13+Assumptions!B5 -> 2450 | G8: =Assumptions!B9 -> 450 | H8: =E8*F8 -> 441000 | I8: =E8*G8 -> 81000 | J8: Mult=2; C4 token-matched to C1 per design
A9: Task A: Repair stage (C1 only) | B9: =Assumptions!B16 -> 30 | C9: =Assumptions!B11 -> 1.5 | D9: =Assumptions!B18 -> 3 | E9: =B9*C9*D9 -> 135 | F9: =Assumptions!B13+Assumptions!B5+Assumptions!B9 -> 2900 | G9: =Assumptions!B10 -> 1800 | H9: =E9*F9 -> 391500 | I9: =E9*G9 -> 243000 | J9: Mult=avg_repair_passes
A10: Task B: Story draft from gold spec (C1,C2,C3) | B10: =Assumptions!B16 -> 30 | C10: 3 | D10: =Assumptions!B18 -> 3 | E10: =B10*C10*D10 -> 270 | F10: =Assumptions!B13+Assumptions!B6 -> 2250 | G10: =Assumptions!B5 -> 2200 | H10: =E10*F10 -> 607500 | I10: =E10*G10 -> 594000 | J10: Mult=3; 180 total per SS4 (30x3x2)
A11: Task B: Plan+review+repair overhead (C1) | B11: =Assumptions!B16 -> 30 | C11: 1 | D11: =Assumptions!B18 -> 3 | E11: =B11*C11*D11 -> 90 | F11: =Assumptions!B13+Assumptions!B6+Assumptions!B5 -> 4450 | G11: =(Assumptions!B8)+(Assumptions!B9+Assumptions!B10)*Assumptions!B11 -> 4375 | H11: =E11*F11 -> 400500 | I11: =E11*G11 -> 393750 | J11: Mult=1; bundled approximation of C1's Task B pipeline overhead
A12: Task C: Spec extraction from source (C1) | B12: =Assumptions!B16 -> 30 | C12: 1 | D12: =Assumptions!B18 -> 3 | E12: =B12*C12*D12 -> 90 | F12: =Assumptions!B13+Assumptions!B5 -> 2450 | G12: =Assumptions!B6 -> 2000 | H12: =E12*F12 -> 220500 | I12: =E12*G12 -> 180000 | J12: Mult=1
A13: Task C: 6 variant drafts/item (C1 full pipeline) | B13: =Assumptions!B16 -> 30 | C13: 1 | D13: =Assumptions!B18 -> 3 | E13: =B13*C13*D13 -> 90 | F13: =Assumptions!B13+Assumptions!B6 -> 2250 | G13: =(Assumptions!B8)+Assumptions!B5+(Assumptions!B9+Assumptions!B10)*Assumptions!B11 -> 6575 | H13: =E13*F13 -> 202500 | I13: =E13*G13 -> 591750 | J13: Mult=6; 360 total per SS4 (30x6x2)
A14: Task D: Scratch story + 6 variants (C1, 7/item) | B14: =Assumptions!B17 -> 10 | C14: =Assumptions!B21 -> 7 | D14: =Assumptions!B18 -> 3 | E14: =B14*C14*D14 -> 210 | F14: =Assumptions!B13+Assumptions!B6 -> 2250 | G14: =(Assumptions!B8)+Assumptions!B5+(Assumptions!B9+Assumptions!B10)*Assumptions!B11 -> 6575 | H14: =E14*F14 -> 472500 | I14: =E14*G14 -> 1380750 | J14: Mult=taskD_outputs_per_item; 140 total per SS4 (10x7x2)
A15: Gold spec model-drafting (SS2.2, one-time) | B15: =Assumptions!B16 -> 30 | C15: 1 | D15: 1 | E15: =B15*C15*D15 -> 30 | F15: =Assumptions!B13+Assumptions!B5 -> 2450 | G15: =Assumptions!B6 -> 2000 | H15: =E15*F15 -> 73500 | I15: =E15*G15 -> 60000 | J15: Mult=1, Gens=1 (single model, one-time)
A16: Parallel-spec translation (SS2.4, one-time) | B16: 6 | C16: 1 | D16: 1 | E16: =B16*C16*D16 -> 6 | F16: =Assumptions!B13+Assumptions!B6 -> 2250 | G16: =Assumptions!B6 -> 2000 | H16: =E16*F16 -> 13500 | I16: =E16*G16 -> 12000 | J16: Negligible; included for completeness
A17: TOTAL — Generation side (all generator families combined) | E17: =SUM(E5:E16) -> 2001 | H17: =SUM(H5:H16) -> 3669900 | I17: =SUM(I5:I16) -> 5156250

Sheet Judging Tokens
A1: Judging-Side Token Estimate (call counts from design doc SS5.6, already totalled across 3 judge families)
A3: Instrument | B3: Model-judge calls | C3: Input tok/call | D3: Output tok/call | E3: Total Input Tokens | F3: Total Output Tokens | G3: % of judging total (input) | H3: RQ | I3: Derivation
A4: S1 Specificity screening | B4: 2880 | C4: 150 | D4: 30 | E4: =B4*C4 -> 432000 | F4: =B4*D4 -> 86400 | G4: =E4/$E$12 -> 0.015604681 | H4: RQ3 | I4: 1 spec value + criteria in; 3 binary checks out.
A5: S2 Gold recovery | B5: 2160 | C5: 250 | D5: 50 | E5: =B5*C5 -> 540000 | F5: =B5*D5 -> 108000 | G5: =E5/$E$12 -> 0.019505852 | H5: RQ3 | I5: Extracted value + gold value + criteria in; 3-level judgement + brief rationale out.
A6: A1 Dimension ID (+A2 bundled) | B6: 1440 | C6: 4600 | D6: 90 | E6: =B6*C6 -> 6624000 | F6: =B6*D6 -> 129600 | G6: =E6/$E$12 -> 0.23927178 | H6: RQ1,RQ5 | I6: Source+variant story pair + dimension list in; choice+rationale+A2 follow-up out.
A7: A3 Spec-story matching | B7: 720 | C7: 6400 | D7: 60 | E7: =B7*C7 -> 4608000 | F7: =B7*D7 -> 43200 | G7: =E7/$E$12 -> 0.16644993 | H7: RQ1,RQ2 | I7: 1 spec + 2 stories in; choice+rationale out.
A8: A4 Story-spec attribution | B8: 720 | C8: 8200 | D8: 60 | E8: =B8*C8 -> 5904000 | F8: =B8*D8 -> 43200 | G8: =E8/$E$12 -> 0.21326398 | H8: RQ1,RQ2 | I8: 1 story + 3 specs in; choice+rationale out.
A9: A5 Sub-dimension recovery | B9: 1620 | C9: 2400 | D9: 30 | E9: =B9*C9 -> 3888000 | F9: =B9*D9 -> 48600 | G9: =E9/$E$12 -> 0.14044213 | H9: RQ1 | I9: 1 story + 4 candidate values in; single choice out.
A10: A6 Premise attribution | B10: 360 | C10: 2600 | D10: 30 | E10: =B10*C10 -> 936000 | F10: =B10*D10 -> 10800 | G10: =E10/$E$12 -> 0.033810143 | H10: calib. | I10: 1 story + 3 premises in; single choice out.
A11: Q1 Pairwise preference | B11: 1080 | C11: 4400 | D11: 120 | E11: =B11*C11 -> 4752000 | F11: =B11*D11 -> 129600 | G11: =E11/$E$12 -> 0.1716515 | H11: RQ4 | I11: 2 full stories in; preference+consistency+brief rationale out.
A12: TOTAL — Judging side (all 3 judge families combined) | B12: =SUM(B4:B11) -> 10980 | E12: =SUM(E4:E11) -> 27684000 | F12: =SUM(F4:F11) -> 599400
